pytkdocs_tweaks/__init__.py
pytkdocs_tweaks-0.0.8.dist-info/METADATA
pytkdocs_tweaks-0.0.8.dist-info/WHEEL
pytkdocs_tweaks-0.0.8.dist-info/licenses/LICENSE
pytkdocs_tweaks-0.0.8.dist-info/RECORD
