Metadata-Version: 2.1
Name: pytkdocs_tweaks
Version: 0.0.8
Summary: Some custom tweaks to the results produced by pytkdocs (part of mkdocstrings).
Project-URL: repository, https://github.com/patrick-kidger/pytkdocs_tweaks
Author-email: Patrick Kidger <contact@kidger.site>
License:                                  Apache License
License-File: LICENSE
Keywords: documentation,mkdocs,mkdocs-material,mkdocstrings
Classifier: Development Status :: 3 - Alpha
Classifier: Intended Audience :: Developers
Classifier: License :: OSI Approved :: Apache Software License
Classifier: Natural Language :: English
Classifier: Programming Language :: Python :: 3
Requires-Python: ~=3.8
Requires-Dist: pytkdocs>=0.15.0
